autocensus/__init__.py
autocensus/api.py
autocensus/constants.py
autocensus/errors.py
autocensus/geography.py
autocensus/query.py
autocensus/utilities.py
autocensus-2.2.1.dist-info/METADATA
autocensus-2.2.1.dist-info/WHEEL
autocensus-2.2.1.dist-info/top_level.txt
autocensus-2.2.1.dist-info/RECORD
