Metadata-Version: 2.2
Name: autocensus
Version: 2.2.1
Summary: A tool for collecting ACS and geospatial data from the Census API
Author-email: Christopher Setzer <cmsetzer.github@gmail.com>
Project-URL: Repository, https://github.com/cmsetzer/autocensus
Keywords: census,acs,api,data
Classifier: Intended Audience :: Developers
Classifier: Intended Audience :: Science/Research
Requires-Python: <4.0,>=3.10
Requires-Dist: geopandas>=1.0.1
Requires-Dist: httpx>=0.28.1
Requires-Dist: nest-asyncio>=1.6.0
Requires-Dist: pandas>=2.2.3
Requires-Dist: platformdirs>=4.3.6
Requires-Dist: pyogrio>=0.10.0
Requires-Dist: shapely>=2.0.7
Requires-Dist: tenacity>=9.0.0
Requires-Dist: typing-extensions>=4.12.2
Requires-Dist: us>=3.2.0
Requires-Dist: yarl>=1.18.3
